Workbook
Name aporte: 'Calculadora '!$D$17
Name patrimonio: 'Calculadora '!$D$20
Name qtd_anos: 'Calculadora '!$D$18
Name rendimento_carteira: 'Calculadora '!$D$13
Name salario: 'Calculadora '!$D$12
Name sugestao_investimento: 'Calculadora '!$D$14
Name taxa_mensal: 'Calculadora '!$D$19

Sheet Calculadora 
B11: CONFIGURAÇÕES
B12: Salário | D12: 3000
B13: Rendimento Carteira | D13: 0.009
B14: Sugestão de Investimento (20%) | D14: =D12*20% -> 600
B16: INVESTIMENTO MENSAL
B17: Quanto investir por mês ? | D17: =sugestao_investimento -> 600
B18: Por Quantos Anos ? | D18: 3
B19: Taxa de Rendimento mensal ? | D19: =rendimento_carteira -> 0.009
B20: Patrimônio acumulado ? | D20: =FV(taxa_mensal,qtd_anos*12,aporte*-1) -> 25376.325
B21: Dividendos Mensais ? | D21: =patrimonio*rendimento_carteira -> 228.38692
B23: Cenários | D23: Dividendo
A24: 2 | B24: Quanto em 2 Anos ? | C24: =FV($D$19,$A24*12,$D$17*-1) -> 15993.586 | D24: =C24*rendimento_carteira -> 143.94228
A25: 5 | B25: Quanto em 5 Anos ? | C25: =FV($D$19,$A25*12,$D$17*-1) -> 47457.788 | D25: =C25*rendimento_carteira -> 427.12009
A26: 10 | B26: Quanto em 10 Anos ? | C26: =FV($D$19,$A26*12,$D$17*-1) -> 128699.2 | D26: =C26*rendimento_carteira -> 1158.2928
A27: 20 | B27: Quanto em 20 Anos ? | C27: =FV($D$19,$A27*12,$D$17*-1) -> 505850.66 | D27: =C27*rendimento_carteira -> 4552.656
A28: 30 | B28: Quanto em 30 Anos ? | C28: =FV($D$19,$A28*12,$D$17*-1) -> 1611088.5 | D28: =C28*rendimento_carteira -> 14499.797
B32: PERFIL | C32: Moderado
B33: VALOR A SER INVESTIDO POR MÊS | C33: =aporte -> 600
B35: TIPO DE FII | C35: Percentual Sugerido | D35: Valores
B36: PAPEL | C36: =_xlfn.XLOOKUP($C$32&"-"&B36,DExPARA!A:A,DExPARA!D:D) -> 0.32 | D36: =C36*$C$33 -> 192
B37: TIJOLO | C37: =_xlfn.XLOOKUP($C$32&"-"&B37,DExPARA!A:A,DExPARA!D:D) -> 0.35 | D37: =C37*$C$33 -> 210
B38: HÍBRIDOS | C38: =_xlfn.XLOOKUP($C$32&"-"&B38,DExPARA!A:A,DExPARA!D:D) -> 0.08 | D38: =C38*$C$33 -> 48
B39: FOFs | C39: =_xlfn.XLOOKUP($C$32&"-"&B39,DExPARA!A:A,DExPARA!D:D) -> 0.05 | D39: =C39*$C$33 -> 30
B40: DESENVOLVIMENTO | C40: =_xlfn.XLOOKUP($C$32&"-"&B40,DExPARA!A:A,DExPARA!D:D) -> 0.1 | D40: =C40*$C$33 -> 60
B41: HOTELARIAS | C41: =_xlfn.XLOOKUP($C$32&"-"&B41,DExPARA!A:A,DExPARA!D:D) -> 0.1 | D41: =C41*$C$33 -> 60
D42: =SUM(D36:D41) -> 600

Sheet DExPARA
A2: CHAVE | B2: PERFIL | C2: TIPO DE FII | D2: %
A3: =B3&"-"&C3 -> Conservador-PAPEL | B3: Conservador | C3: PAPEL | D3: 0.3
A4: =B4&"-"&C4 -> Conservador-TIJOLO | B4: Conservador | C4: TIJOLO | D4: 0.5
A5: =B5&"-"&C5 -> Conservador-HÍBRIDOS | B5: Conservador | C5: HÍBRIDOS | D5: 0.1
A6: =B6&"-"&C6 -> Conservador-FOFs | B6: Conservador | C6: FOFs | D6: 0.1
A7: =B7&"-"&C7 -> Conservador-DESENVOLVIMENTO | B7: Conservador | C7: DESENVOLVIMENTO | D7: 0
A8: =B8&"-"&C8 -> Conservador-HOTELARIAS | B8: Conservador | C8: HOTELARIAS | D8: 0
A9: =B9&"-"&C9 -> Moderado-PAPEL | B9: Moderado | C9: PAPEL | D9: 0.32
A10: =B10&"-"&C10 -> Moderado-TIJOLO | B10: Moderado | C10: TIJOLO | D10: 0.35
A11: =B11&"-"&C11 -> Moderado-HÍBRIDOS | B11: Moderado | C11: HÍBRIDOS | D11: 0.08
A12: =B12&"-"&C12 -> Moderado-FOFs | B12: Moderado | C12: FOFs | D12: 0.05
A13: =B13&"-"&C13 -> Moderado-DESENVOLVIMENTO | B13: Moderado | C13: DESENVOLVIMENTO | D13: 0.1
A14: =B14&"-"&C14 -> Moderado-HOTELARIAS | B14: Moderado | C14: HOTELARIAS | D14: 0.1
... A20: =B20&"-"&C20 -> Agressivo-HOTELARIAS | B20: Agressivo | C20: HOTELARIAS | D20: 0.1
